conveyor/__init__.py
conveyor/client/__init__.py
conveyor/runtime/__init__.py
conveyor/runtime/driver.py
conveyor/runtime/driver_logger.py
conveyor/runtime/driver_logger_handler.py
conveyor/runtime/exceptions.py
conveyor/runtime/manager.py
conveyor/runtime/nat_connection.py
conveyor_py-0.0.3.dist-info/licenses/LICENSE
conveyor_py-0.0.3.dist-info/METADATA
conveyor_py-0.0.3.dist-info/WHEEL
conveyor_py-0.0.3.dist-info/top_level.txt
conveyor_py-0.0.3.dist-info/RECORD
