Metadata-Version: 2.4
Name: conveyor.py
Version: 0.0.3
Summary: Conveyor CI Python Client
Home-page: https://github.com/open-ug/conveyor.py
Author: Beingana Jim Junior
Author-email: jim@open.ug
License: MIT
Keywords: cicd,continuous integration,continuous deployment,devops,python client,conveyor
Classifier: Environment :: Web Environment
Classifier: Intended Audience :: Developers
Classifier: License :: OSI Approved :: MIT License
Classifier: Operating System :: OS Independent
Classifier: Programming Language :: Python
Classifier: Programming Language :: Python :: 3
Classifier: Topic :: Internet :: WWW/HTTP
Classifier: Topic :: Internet :: WWW/HTTP :: Dynamic Content
Requires-Python: >=3.6
License-File: LICENSE
Requires-Dist: requests>=2.32.4
Requires-Dist: nats-py>=2.10.0
Requires-Dist: httpx>=0.28.1
Dynamic: license-file
